Metadata-Version: 1.0
Name: qSMTP
Version: 1.0.0
Summary: private module for quickly sending mail to others
Home-page: UNKNOWN
Author: zwy
Author-email: zuowangyang@foxmail.com
License: MIT License
Keywords: SMTP,quickly STMP
Platform: any
